decat/__init__.py
decat/__main__.py
decat/__settings__.py
decat/.data/__init__.py
decat/.data/vocabulary/en/frequency.json
decat/.data/vocabulary/en/tokens.json
decat/core/__init__.py
decat/core/model.py
decat/parsers/__init__.py
decat/parsers/input_parser/__init__.py
decat/parsers/input_parser/_parser.py
decat/parsers/input_parser/_validators.py
decat-1.0.3.dist-info/LICENSE
decat-1.0.3.dist-info/METADATA
decat-1.0.3.dist-info/WHEEL
decat-1.0.3.dist-info/entry_points.txt
decat-1.0.3.dist-info/top_level.txt
decat-1.0.3.dist-info/RECORD
