Metadata-Version: 2.1
Name: decat
Version: 1.0.3
Summary: De-concatenate strings that do not have white-spaces.
Home-page: https://github.com/sudoMode/Decat
Author: Mandeep Singh
Author-email: singh.mandeep22207@gmail.com
License: MIT
Project-URL: Source, https://github.com/sudoMode/Decat
Project-URL: Bug Tracker, https://github.com/sudoMode/Decat/issues
Keywords: nlp,text mining
Classifier: Development Status :: 5 - Production/Stable
Classifier: Intended Audience :: Developers
Classifier: License :: OSI Approved :: MIT License
Classifier: Programming Language :: Python :: 3.6
Classifier: Programming Language :: Python :: 3.7
Classifier: Programming Language :: Python :: 3.8
Classifier: Programming Language :: Python :: 3.9
Classifier: Operating System :: OS Independent
Requires-Python: >=3.6
License-File: LICENSE
